Metadata-Version: 2.1
Name: nonebot-plugin-helper-plus
Version: 0.1.7
Summary: 带有阻断（屏蔽）指定群聊 消息/指令 功能的helper。
Author: fR0Z863xF
License: GNU GENERAL PUBLIC LICENSE
Project-URL: Homepage, https://github.com/fR0Z863xF/nonebot-plugin-helper-plus
Project-URL: Repository, https://github.com/fR0Z863xF/nonebot-plugin-helper-plus
Requires-Python: >=3.8
License-File: LICENSE
Requires-Dist: nonebot2 >=2.0.0rc2
Requires-Dist: nonebot-adapter-onebot >=2.1.0
